README.md
setup.py
fsinc/__init__.py
fsinc/fastgl.py
fsinc/fsinc_1d.py
fsinc/fsinc_1d_nu.py
fsinc/fsinc_1d_u.py
fsinc/fsinc_2d.py
fsinc/fsinc_2d_nu.py
fsinc/fsinc_2d_u.py
fsinc/jacobian.py
fsinc.egg-info/PKG-INFO
fsinc.egg-info/SOURCES.txt
fsinc.egg-info/dependency_links.txt
fsinc.egg-info/requires.txt
fsinc.egg-info/top_level.txt
tests/__init__.py
tests/fsinc_interp_1d_test.py
tests/fsinc_interp_2d_test.py
tests/offset_test.py
tests/sinc1d_test.py
tests/sinc2d_test.py
tests/sincsq1d_test.py
tests/sincsq2d_test.py